{
  "image": {
    "id": "6e38188b-9f1c-470c-b8ce-6105eb132d42",
    "name": "Screenshot_2025-07-19_038.png",
    "path": "images/Screenshot_2025-07-19_038.png",
    "width": 1920,
    "height": 1080
  },
  "annotations": [
    {
      "id": "manual-8acd7e05-9f1b-4596-b754-155601ebed22",
      "label": "Button",
      "value": "button",
      "bbox": {
        "x": 1450,
        "y": 538,
        "width": 376,
        "height": 207
      },
      "author": "manual",
      "score": 1.0
    },
    {
      "id": "manual-1f3c5a2d-7f9d-4feb-af7f-4b9b4c28cc75",
      "label": "Button",
      "value": "button",
      "bbox": {
        "x": 61,
        "y": 732,
        "width": 416,
        "height": 57
      },
      "author": "manual",
      "score": 1.0
    },
    {
      "id": "manual-3480e7a5-086b-46ec-ab05-1070173abc3f",
      "label": "Radio",
      "value": "radio",
      "bbox": {
        "x": 736,
        "y": 623,
        "width": 369,
        "height": 189
      },
      "author": "manual",
      "score": 1.0
    }
  ]
}