{
  "image": {
    "id": "99a09020-806e-4dc6-aba1-2f4a63b7cd54",
    "name": "Screenshot_2025-07-19_079.png",
    "path": "images/Screenshot_2025-07-19_079.png",
    "width": 1920,
    "height": 1080
  },
  "annotations": [
    {
      "id": "manual-9631021d-7f49-4676-a6c6-94c4b7a78441",
      "label": "Dropdown",
      "value": "dropdown",
      "bbox": {
        "x": 1134,
        "y": 618,
        "width": 141,
        "height": 30
      },
      "author": "manual",
      "score": 1.0
    },
    {
      "id": "manual-70551ac9-084b-47c6-9659-2177f3b84e1b",
      "label": "Radio",
      "value": "radio",
      "bbox": {
        "x": 323,
        "y": 898,
        "width": 170,
        "height": 83
      },
      "author": "manual",
      "score": 1.0
    },
    {
      "id": "manual-796fd024-6bd6-4228-ab74-ccae359345c6",
      "label": "Button",
      "value": "button",
      "bbox": {
        "x": 1593,
        "y": 990,
        "width": 300,
        "height": 102
      },
      "author": "manual",
      "score": 1.0
    }
  ]
}